PyAutoCoder/PyAutoCoder.py
PyAutoCoder-1.dist-info/LICENSE
PyAutoCoder-1.dist-info/METADATA
PyAutoCoder-1.dist-info/WHEEL
PyAutoCoder-1.dist-info/entry_points.txt
PyAutoCoder-1.dist-info/top_level.txt
PyAutoCoder-1.dist-info/RECORD
